polars_as_config/__init__.py
polars_as_config/config.py
polars_as_config/json_to_polars.py
polars_as_config/polars_to_json.py
polars_as_config/template_blocks/block_input.json
polars_as_config-1.2.1.dist-info/METADATA
polars_as_config-1.2.1.dist-info/WHEEL
polars_as_config-1.2.1.dist-info/licenses/LICENSE
polars_as_config-1.2.1.dist-info/RECORD
