Metadata-Version: 2.4
Name: polars-as-config
Version: 1.2.1
Summary: A Python package for using Polars from configuration
Project-URL: Homepage, https://github.com/mavills/polars-as-config
Project-URL: Repository, https://github.com/mavills/polars-as-config.git
Project-URL: Issues, https://github.com/mavills/polars-as-config/issues
Author: Mavills
License:                                  Apache License
License-File: LICENSE
Classifier: Development Status :: 3 - Alpha
Classifier: Intended Audience :: Developers
Classifier: License :: OSI Approved :: Apache Software License
Classifier: Programming Language :: Python :: 3
Classifier: Programming Language :: Python :: 3.12
Classifier: Programming Language :: Python :: 3.13
Requires-Python: >=3.11
Requires-Dist: polars
